RedDownloader/RedDownloader.py
RedDownloader/__init__.py
reddownloader-4.4.1.dist-info/licenses/LICENSE
reddownloader-4.4.1.dist-info/METADATA
reddownloader-4.4.1.dist-info/WHEEL
reddownloader-4.4.1.dist-info/top_level.txt
reddownloader-4.4.1.dist-info/RECORD
