Metadata-Version: 2.4
Name: RedDownloader
Version: 4.4.1
Summary: A package to download Reddit hosted videos easily and efficiently.
Home-page: https://github.com/JackhammerYT/RedVidDownloader
Author: Arnav Bajaj
Author-email: arnavbajaj9@gmail.com
Project-URL: Bug Tracker, https://github.com/JackhammerYT/RedDownloader/issues
Classifier: Programming Language :: Python :: 3
Classifier: License :: OSI Approved :: GNU General Public License v3 (GPLv3)
Classifier: Operating System :: OS Independent
Requires-Python: >=3.6
License-File: LICENSE
Requires-Dist: requests
Requires-Dist: tqdm==4.62.3
Requires-Dist: moviepy
Requires-Dist: pytube
Dynamic: author
Dynamic: author-email
Dynamic: classifier
Dynamic: description
Dynamic: description-content-type
Dynamic: home-page
Dynamic: license-file
Dynamic: project-url
Dynamic: requires-dist
Dynamic: requires-python
Dynamic: summary
